{
  "tableOfContentsUri": "/general-conference/2023/10",
  "meta": {
    "scopedClassName": "global-template-mobile_article",
    "archived": false,
    "canonicalUrl": "/general-conference/2023/10/15christofferson?lang=spa",
    "pageAttributes": {
      "data-asset-id": "21914329c483431dbd790a8194809c46",
      "data-content-type": "general-conference-talk",
      "itemscope": "",
      "itemtype": "http://schema.org/Article",
      "data-uri": "/general-conference/2023/10/15christofferson",
      "data-aid": "156927064",
      "xmlns:xsi": "http://www.w3.org/2001/XMLSchema-instance",
      "lang": "spa",
      "data-aid-version": "4",
      "data-orig-id": "d600024df9fe4fb3ab6c123ab792c9cd"
    },
    "ogTagImageUrl": "https://assets.churchofjesuschrist.org/53/0c/530cda21e5c78969b5ab0ce9c093269420e4d10a/530cda21e5c78969b5ab0ce9c093269420e4d10a.jpeg",
    "audio": [{
      "mediaUrl": "https://media2.ldscdn.org/assets/general-conference/october-2023-general-conference/2023-10-1050-d-todd-christofferson-32k-spa.mp3",
      "variant": "audio"
    }],
    "title": "El poder para sellar",
    "contentType": "text/html",
    "structuredData": "{\"@context\":\"https://schema.org\",\"@type\":\"WebPage\",\"datePublished\":\"2023-10-30T00:00:00.000Z\"}"
  },
  "verified": true,
  "pids": [
    [
      "156927064",
      {"key": "156927064"}
    ],
    [
      "157004912",
      {"key": "157004912"}
    ],
    [
      "157004913",
      {"key": "157004913"}
    ],
    [
      "157004914",
      {"key": "157004914"}
    ],
    [
      "157004915",
      {"key": "157004915"}
    ],
    [
      "157004917",
      {"key": "157004917"}
    ],
    [
      "157004919",
      {"key": "157004919"}
    ],
    [
      "157004921",
      {"key": "157004921"}
    ],
    [
      "157004923",
      {"key": "157004923"}
    ],
    [
      "157004925",
      {"key": "157004925"}
    ],
    [
      "157004927",
      {"key": "157004927"}
    ],
    [
      "157004929",
      {"key": "157004929"}
    ],
    [
      "157004931",
      {"key": "157004931"}
    ],
    [
      "157004933",
      {"key": "157004933"}
    ],
    [
      "157004935",
      {"key": "157004935"}
    ],
    [
      "157004937",
      {"key": "157004937"}
    ],
    [
      "157004939",
      {"key": "157004939"}
    ],
    [
      "157004941",
      {"key": "157004941"}
    ],
    [
      "157004943",
      {"key": "157004943"}
    ],
    [
      "157004944",
      {"key": "157004944"}
    ],
    [
      "157004946",
      {"key": "157004946"}
    ],
    [
      "157004948",
      {"key": "157004948"}
    ],
    [
      "157004950",
      {"key": "157004950"}
    ],
    [
      "157004952",
      {"key": "157004952"}
    ],
    [
      "157004954",
      {"key": "157004954"}
    ],
    [
      "157004955",
      {"key": "157004955"}
    ],
    [
      "157004957",
      {"key": "157004957"}
    ],
    [
      "157004959",
      {"key": "157004959"}
    ],
    [
      "157004961",
      {"key": "157004961"}
    ],
    [
      "157004963",
      {"key": "157004963"}
    ],
    [
      "157004965",
      {"key": "157004965"}
    ],
    [
      "157004967",
      {"key": "157004967"}
    ],
    [
      "157004969",
      {"key": "157004969"}
    ],
    [
      "157004971",
      {"key": "157004971"}
    ],
    [
      "157004973",
      {"key": "157004973"}
    ],
    [
      "157004975",
      {"key": "157004975"}
    ],
    [
      "157004977",
      {"key": "157004977"}
    ],
    [
      "157004979",
      {"key": "157004979"}
    ],
    [
      "157004982",
      {"key": "157004982"}
    ],
    [
      "157004984",
      {"key": "157004984"}
    ],
    [
      "157004986",
      {"key": "157004986"}
    ],
    [
      "157004989",
      {"key": "157004989"}
    ],
    [
      "157004992",
      {"key": "157004992"}
    ],
    [
      "157004994",
      {"key": "157004994"}
    ],
    [
      "157004997",
      {"key": "157004997"}
    ],
    [
      "157005000",
      {"key": "157005000"}
    ],
    [
      "157005003",
      {"key": "157005003"}
    ],
    [
      "157005006",
      {"key": "157005006"}
    ],
    [
      "157005009",
      {"key": "157005009"}
    ],
    [
      "157005013",
      {"key": "157005013"}
    ],
    [
      "157005017",
      {"key": "157005017"}
    ],
    [
      "157005021",
      {"key": "157005021"}
    ],
    [
      "157005026",
      {"key": "157005026"}
    ]
  ],
  "uri": "/general-conference/2023/10/15christofferson",
  "content": {
    "head": {
      "links": [{
        "orig-type": "text/css",
        "rel": "stylesheet",
        "href": "https://ips-cdn-edge.churchofjesuschrist.org/styles/css/style_global-template-mobile_article_scoped.css",
        "type": "array"
      }],
      "scripts": [],
      "page-meta-social": {
        "pageMeta": {
          "description": "El élder Christofferson enseña que el poder para sellar, el cual valida todas las ordenanzas del sacerdocio y las hace vinculantes tanto en la tierra como en el cielo, es crucial para el recogimiento de Israel.",
          "title": "El poder para sellar"
        },
        "pageSocial": {
          "description": "El élder Christofferson enseña que el poder para sellar, el cual valida todas las ordenanzas del sacerdocio y las hace vinculantes tanto en la tierra como en el cielo, es crucial para el recogimiento de Israel.",
          "title": "El poder para sellar"
        }
      }
    },
    "body": "<header>\n\n<video controls=\"controls\" poster=\"https://assets.churchofjesuschrist.org/53/0c/530cda21e5c78969b5ab0ce9c093269420e4d10a/530cda21e5c78969b5ab0ce9c093269420e4d10a.jpeg\" data-video-title=\"El poder para sellar\" data-video-description=\"El élder Christofferson enseña que el poder para sellar, el cual valida todas las ordenanzas del sacerdocio y las hace vinculantes tanto en la tierra como en el cielo, es crucial para el recogimiento de Israel.\" data-video-id=\"6338158222112\" data-ip=\"Download and Streaming                            \" data-duration=\"865399\" data-assetId=\"466918515fc611eeb2c0eeeeac1ec72fc275999a\" data-ref-id=\"FC5DE7A63A00C9F0632F80FA89DF5F2152D84CC6\" id=\"video2\"><source src=\"https://mediasrv.churchofjesuschrist.org/media-services/GA/type/6338158222112/hls.m3u8\" type=\"application/vnd.apple.mpegurl\" data-width=\"1920\" data-height=\"1080\" data-file-size=\"288991140\"/><source src=\"https://media2.ldscdn.org/assets/general-conference/october-2023-general-conference/2023-10-1050-d-todd-christofferson-360p-spa.mp4\" type=\"video/mp4\" data-width=\"480\" data-height=\"360\" data-file-size=\"80234773\"/><source src=\"https://media2.ldscdn.org/assets/general-conference/october-2023-general-conference/2023-10-1050-d-todd-christofferson-720p-spa.mp4\" type=\"video/mp4\" data-width=\"1280\" data-height=\"720\" data-file-size=\"208590615\"/><source src=\"https://media2.ldscdn.org/assets/general-conference/october-2023-general-conference/2023-10-1050-d-todd-christofferson-1080p-spa.mp4\" type=\"video/mp4\" data-width=\"1920\" data-height=\"1080\" data-file-size=\"288991140\"/><\/video><h1 data-aid=\"157004912\" id=\"title1\">El poder para sellar<\/h1>\n<div class=\"byline\">\n<p class=\"author-name\" data-aid=\"157004913\" id=\"author1\">Por el élder D. Todd Christofferson<\/p>\n<p class=\"author-role\" data-aid=\"157004914\" id=\"author2\">Del Cuórum de los Doce Apóstoles<\/p>\n<\/div>\n<p class=\"kicker\" data-aid=\"157004915\" id=\"kicker1\">El poder para sellar hace que la salvación individual y la exaltación familiar estén universalmente al alcance de los hijos de Dios.<\/p>\n<\/header>\n<div class=\"body-block\">\n<p data-aid=\"157004917\" id=\"p1\">Se ha profetizado, al menos desde los tiempos de Isaías<a class=\"note-ref\" href=\"#note1\"><sup class=\"marker\">1<\/sup><\/a>, que, en los últimos días, el antiguo pueblo del convenio del Señor, la casa de Israel, debía ser \u201c[congregado] de su larga dispersión, desde las islas del mar y desde las cuatro partes de la tierra\u201d<a class=\"note-ref\" href=\"#note2\"><sup class=\"marker\">2<\/sup><\/a>, y restaurado a \u201clas tierras de su herencia\u201d<a class=\"note-ref\" href=\"#note3\"><sup class=\"marker\">3<\/sup><\/a>. El presidente Russell M. Nelson ha hablado con frecuencia y con poder acerca de este recogimiento, designándolo como \u201clo más importante que se está llevando a cabo hoy en la tierra\u201d<a class=\"note-ref\" href=\"#note4\"><sup class=\"marker\">4<\/sup><\/a>.<\/p>\n<p data-aid=\"157004919\" id=\"p2\">¿Cuál es el propósito de este recogimiento?<\/p>\n<p data-aid=\"157004921\" id=\"p3\">Mediante revelación al profeta José Smith, el Señor explicó que uno de los propósitos es proteger al pueblo del convenio: \u201cA fin de que el recogimiento en la tierra de Sion y sus estacas [serán] para defensa y para refugio contra la tempestad y contra la ira, cuando sea derramada sin mezcla sobre toda la tierra\u201d<a class=\"note-ref\" href=\"#note5\"><sup class=\"marker\">5<\/sup><\/a>. En este contexto, \u201cira\u201d podría entenderse como las consecuencias naturales de una desobediencia generalizada a las leyes y los mandamientos de Dios.<\/p>\n<p data-aid=\"157004923\" id=\"p4\">Más importante aún es que el recogimiento tiene el propósito de brindar todas las bendiciones de salvación y exaltación a todos las personas que deseen recibirlas. Es la manera en que se cumplen las promesas del convenio hechas a Abraham. El Señor le dijo a Abraham que en su descendencia y sacerdocio \u201cser[ía]n bendecidas todas las familias de la tierra, sí, con las bendiciones del evangelio, que son las bendiciones de salvación, sí, de vida eterna\u201d<a class=\"note-ref\" href=\"#note6\"><sup class=\"marker\">6<\/sup><\/a>. El presidente Nelson lo expresó de esta manera: \u201cCuando aceptamos el Evangelio y somos bautizados, tomamos sobre nosotros el sagrado nombre de Jesucristo. El bautismo es la puerta que conduce a que lleguemos a ser coherederos de todas las promesas que el Señor extendió en la antigüedad a Abraham, Isaac, Jacob y su posteridad\u201d<a class=\"note-ref\" href=\"#note7\"><sup class=\"marker\">7<\/sup><\/a>.<\/p>\n<p data-aid=\"157004925\" id=\"p5\">En 1836, Moisés se apareció al profeta José Smith en el Templo de Kirtland y le \u201centregó las llaves del recogimiento de Israel de las cuatro partes de la tierra\u201d<a class=\"note-ref\" href=\"#note8\"><sup class=\"marker\">8<\/sup><\/a>. En esa misma ocasión, se apareció Elías y \u201centregó la dispensación del evangelio de Abraham, diciendo que en nosotros y en nuestra descendencia serían bendecidas todas las generaciones después de nosotros\u201d<a class=\"note-ref\" href=\"#note9\"><sup class=\"marker\">9<\/sup><\/a>. Con esa autoridad, nosotros ahora llevamos el Evangelio de Jesucristo \u2014las buenas nuevas de redención por medio de Él\u2014 a todas partes y a todos los pueblos de la tierra, y recogemos en el convenio del Evangelio a todos cuantos lo deseen. Ellos llegan a ser \u201cla descendencia de Abraham, y la iglesia y reino, y los elegidos de Dios\u201d<a class=\"note-ref\" href=\"#note10\"><sup class=\"marker\">10<\/sup><\/a>.<\/p>\n<p data-aid=\"157004927\" id=\"p6\">En esa misma ocasión en el Templo de Kirtland, un tercer mensajero celestial se apareció a José Smith y a Oliver Cowdery. Me refiero a Elías el Profeta, y hoy deseo hablarles sobre la autoridad y las llaves que él restauró<a class=\"note-ref\" href=\"#note11\"><sup class=\"marker\">11<\/sup><\/a>. El poder que da validez a todas las ordenanzas del sacerdocio y las hace vinculantes tanto en la tierra como en el cielo \u2014el poder para sellar\u2014 es crucial para el recogimiento y para preparar a un pueblo del convenio en ambos lados del velo.<\/p>\n<p data-aid=\"157004929\" id=\"p7\">Unos años antes, Moroni había explicado a José Smith que Elías el Profeta traería una autoridad del sacerdocio esencial: \u201cYo os revelaré el sacerdocio, por conducto de Elías el Profeta\u201d<a class=\"note-ref\" href=\"#note12\"><sup class=\"marker\">12<\/sup><\/a>. Más adelante, José Smith explicó: \u201c¿Por qué enviar a Elías? Porque él tiene las llaves de la autoridad para administrar todas las ordenanzas del sacerdocio; y [a no ser que] esa autoridad se dé, las ordenanzas no se podrían administrar en justicia\u201d<a class=\"note-ref\" href=\"#note13\"><sup class=\"marker\">13<\/sup><\/a>, es decir, las ordenanzas no serían válidas ni por el tiempo ni la eternidad<a class=\"note-ref\" href=\"#note14\"><sup class=\"marker\">14<\/sup><\/a>.<\/p>\n<p data-aid=\"157004931\" id=\"p8\">En una enseñanza que está ahora canonizada en un pasaje de las Escrituras en Doctrina y Convenios, el Profeta afirmó: \u201cA algunos les parecerá muy atrevida esta doctrina que discutimos: un poder que registra o ata en la tierra y también en los cielos. Sin embargo, en todas las edades del mundo, cada vez que el Señor ha dado una dispensación del sacerdocio a un hombre o grupo de hombres, por revelación efectiva, siempre se ha dado este poder. De manera que, todo cuanto esos hombres hicieron con autoridad, en el nombre del Señor, y lo hicieron verdadera y fielmente, y llevaron un registro adecuado y fiel de ello, esto llegó a ser una ley en la tierra y en los cielos, y, de acuerdo con los decretos del gran Jehová, no podía anularse\u201d<a class=\"note-ref\" href=\"#note15\"><sup class=\"marker\">15<\/sup><\/a>.<\/p>\n<p data-aid=\"157004933\" id=\"p10\">Tendemos a pensar en la autoridad para sellar como algo que solo se refiere a ciertas ordenanzas del templo, pero esa autoridad es necesaria para hacer que cualquier ordenanza sea válida y vinculante más allá de la muerte<a class=\"note-ref\" href=\"#note16\"><sup class=\"marker\">16<\/sup><\/a>. El poder para sellar confiere un sello de legitimidad sobre su bautismo, por ejemplo, para que este sea reconocido aquí y en el cielo. En definitiva, todas las ordenanzas del sacerdocio se efectúan bajo las llaves del Presidente de la Iglesia y, como explicó el presidente Joseph Fielding Smith: \u201cÉl [el Presidente de la Iglesia] ha puesto el poder para sellar en nuestro sacerdocio porque él posee esas llaves\u201d<a class=\"note-ref\" href=\"#note17\"><sup class=\"marker\">17<\/sup><\/a>.<\/p>\n<p data-aid=\"157004935\" id=\"p11\">Existe otro propósito vital en el recogimiento de Israel que tiene un significado especial cuando hablamos de sellar en la tierra y en el cielo: es la edificación y el funcionamiento de los templos. El profeta José Smith enseñó: \u201c¿Cuál era el objeto del recogimiento del [\u2026] pueblo de Dios en cualquier época del mundo? [\u2026]. El objeto principal era edificar una casa al Señor en la cual Él pudiera revelar a Su pueblo las ordenanzas de Su casa y las glorias de Su reino, y enseñar a la gente el camino de la salvación; porque hay ciertas ordenanzas y principios que, para poder enseñarse y practicarse, deben efectuarse en un lugar o casa edificada para tal propósito\u201d<a class=\"note-ref\" href=\"#note18\"><sup class=\"marker\">18<\/sup><\/a>.<\/p>\n<p data-aid=\"157004937\" id=\"p13\">La validez que el poder para sellar otorga a las ordenanzas del sacerdocio abarca, desde luego, las ordenanzas vicarias efectuadas en el lugar designado por el Señor: Su templo. Aquí vemos la majestuosidad y la santidad del poder para sellar: este hace que la salvación individual y la exaltación familiar estén universalmente al alcance de los hijos de Dios, donde sea y cuando sea que hayan vivido en la tierra. No existe otra teología ni filosofía ni autoridad que se comparen con esta oportunidad que incluye a todos. Este poder para sellar es una manifestación perfecta de la justicia, la misericordia y el amor de Dios.<\/p>\n<p data-aid=\"157004939\" id=\"p14\">Teniendo acceso al poder para sellar, nuestros corazones se vuelven naturalmente hacia quienes nos han antecedido. El recogimiento de los últimos días en el convenio traspasa el velo. En el orden perfecto de Dios, los vivos no pueden experimentar la vida eterna en su plenitud sin forjar vínculos perdurables con \u201clos padres\u201d, nuestros antepasados. Asimismo, el progreso de quienes ya se hallan al otro lado y de quienes aún puede que crucen el velo de la muerte sin el beneficio de los sellamientos no es completo sin las ordenanzas vicarias que los unen a nosotros, sus descendientes, y nosotros a ellos en el orden divino<a class=\"note-ref\" href=\"#note19\"><sup class=\"marker\">19<\/sup><\/a>. El compromiso de ayudarnos unos a otros a través del velo se puede catalogar como una promesa del convenio y forma parte del nuevo y sempiterno convenio. En palabras de José Smith, nosotros deseamos \u201csell[ar] a nuestros muertos para que salgan [con nosotros] en la primera resurrección\u201d<a class=\"note-ref\" href=\"#note20\"><sup class=\"marker\">20<\/sup><\/a>.<\/p>\n<p data-aid=\"157004941\" id=\"p15\">La manifestación más elevada y santa del poder para sellar está en la unión eterna de un hombre y una mujer en matrimonio y en la unión de toda la humanidad a través de todas sus generaciones. Debido a que la autoridad para oficiar en estas ordenanzas es tan sagrada, el Presidente de la Iglesia supervisa personalmente su delegación a otras personas. El presidente Gordon B. Hinckley dijo en una ocasión: \u201cHe dicho muchas veces que si de todo el pesar, las tribulaciones y el dolor de la Restauración no resultara nada más que el poder para sellar del santo sacerdocio para unir a las familias para siempre, entonces habrá valido la pena todo lo que ha costado\u201d<a class=\"note-ref\" href=\"#note21\"><sup class=\"marker\">21<\/sup><\/a>.<\/p>\n<p data-aid=\"157004943\" id=\"p16\">Sin los sellamientos que crean familias eternas y unen generaciones aquí y en el más allá, quedaríamos sin raíces y sin ramas por la eternidad; es decir, sin antepasados ni posteridad. Lo que frustraría el propósito mismo de la creación de la tierra y de nuestra experiencia terrenal es este estado de individuos desconectados, flotando libremente, por un lado, o las conexiones que desafían las relaciones familiares y el matrimonio que Dios ha señalado<a class=\"note-ref\" href=\"#note22\"><sup class=\"marker\">22<\/sup><\/a>, por otro lado. Si esto se convirtiera en la norma, equivaldría a que la tierra sería herida con maldición o \u201ctotalmente asolada\u201d a la venida del Señor<a class=\"note-ref\" href=\"#note23\"><sup class=\"marker\">23<\/sup><\/a>.<\/p>\n<p data-aid=\"157004944\" id=\"p17\">Podemos ver por qué \u201cel matrimonio entre el hombre y la mujer es ordenado por Dios y que la familia es fundamental en el plan del Creador para el destino eterno de Sus hijos\u201d<a class=\"note-ref\" href=\"#note24\"><sup class=\"marker\">24<\/sup><\/a>. Al mismo tiempo, reconocemos que en el imperfecto presente, esta no es la realidad o siquiera una posibilidad realista para algunas personas, pero tenemos esperanza en Cristo. Mientras esperamos en el Señor, el presidente M. Russell Ballard nos recuerda que \u201clas Escrituras y los profetas de los últimos días confirman que toda persona que sea fiel en guardar los convenios del Evangelio tendrá la oportunidad de ser exaltada\u201d<a class=\"note-ref\" href=\"#note25\"><sup class=\"marker\">25<\/sup><\/a>.<\/p>\n<p data-aid=\"157004946\" id=\"p18\">Algunas personas han experimentado circunstancias infelices y perjudiciales en sus familias y sienten pocos deseos de tener una relación familiar eterna. El élder David A. Bednar hizo esta observación: \u201cA ustedes que han experimentado la angustia de un divorcio en su familia o han sentido la agonía de ser defraudados, ¡por favor, recuerden que [el modelo de Dios para las familias] comienza de nuevo con ustedes! Quizás se haya roto un eslabón en la cadena de sus generaciones, pero los otros eslabones rectos y lo que queda de la cadena son eternamente importantes. Ustedes pueden reforzar su cadena e incluso ayudar a restaurar los eslabones rotos. Esa labor se logrará uno por uno\u201d<a class=\"note-ref\" href=\"#note26\"><sup class=\"marker\">26<\/sup><\/a>.<\/p>\n<p data-aid=\"157004948\" id=\"p20\">En el funeral de la hermana Pat Holland, la esposa del élder Jeffrey R. Holland, el pasado mes de julio, el presidente Russell M. Nelson enseñó: \u201cA su tiempo, Patricia y Jeffrey serán unidos nuevamente. Posteriormente se les unirán sus hijos y su posteridad que guarden el convenio para experimentar la plenitud de gozo que Dios tiene reservada para Sus hijos fieles. Sabiendo esto, entendemos que la fecha más importante en la vida de Patricia no fue su fecha de nacimiento ni su fecha de defunción. Su fecha más importante fue el 7 de junio de 1963, cuando ella y Jeff fueron sellados en el Templo de St. George [\u2026]. ¿Por qué es tan importante eso? Porque la razón misma por la que fue creada la tierra es que se pudieran formar familias y fueran selladas unas a otras. La salvación es un asunto individual, pero la exaltación es un asunto familiar. Nadie puede ser exaltado solo\u201d.<\/p>\n<p data-aid=\"157004950\" id=\"p21\">Hace poco, mi esposa y yo acompañamos a una querida amiga en una sala de sellamientos en el Templo de Bountiful, Utah. La conocí en Córdoba, Argentina, cuando ella era una niña. Mi compañero de la misión y yo estábamos contactando personas en un vecindario cercano a la oficina de la misión y ella abrió la puerta cuando tocamos a su vivienda. A su debido tiempo, su madre, ella y sus hermanos se unieron a la Iglesia y se han mantenido fieles. Ella es ahora una mujer encantadora y estuvimos ese día en el templo para sellar a sus difuntos padres y, luego, sellar a mi amiga a ellos.<\/p>\n<p data-aid=\"157004952\" id=\"p22\">Una pareja que, con los años, se han vuelto amigos muy cercanos, representó a los padres en el altar. Fue un momento muy emotivo que fue aún más dulce cuando nuestra amiga argentina fue sellada a sus padres. Solo había seis personas presentes en esa tarde apacible, alejados del mundo y, no obstante, estaba ocurriendo una de las cosas más importantes sobre la tierra. Fue gratificante para mí ver que se completaba el ciclo de mi función y relación con ellos, desde que toqué a su puerta siendo un joven misionero hasta ahora, muchos años más tarde, cuando efectué las ordenanzas de sellamiento que la unieron a ella a sus padres y a las generaciones anteriores.<\/p>\n<p data-aid=\"157004954\" id=\"p23\">Esta escena se repite constantemente en todos los templos del mundo. Es el paso final del recogimiento del pueblo del convenio. Es el privilegio supremo de ser miembro de la Iglesia de Jesucristo. Les prometo que conforme procuren fielmente ese privilegio, en el tiempo o la eternidad, con toda seguridad lo tendrán.<\/p>\n<p data-aid=\"157004955\" id=\"p24\">Testifico que el poder y la autoridad para sellar, restaurados a la tierra por medio de José Smith, son reales; que lo que por ellos se ata en la tierra ciertamente es atado en el cielo. Testifico que el presidente Russell M. Nelson, como Presidente de la Iglesia, es el único hombre en la tierra hoy en día que, por medio de sus llaves, dirige el uso de este poder celestial. Testifico que la Expiación de Jesucristo ha hecho que la inmortalidad sea una certeza y que la posibilidad de las relaciones familiares exaltadas sea una realidad. En el nombre de Jesucristo. Amén.<\/p>\n<\/div>\n<footer class=\"notes\">\n<p class=\"title\" data-aid=\"157004957\" id=\"note_title1\">Notas<\/p>\n<ol class=\"decimal\" data-type=\"marker\" start=\"1\">\n<li data-marker=\"1.\" id=\"note1\" data-full-marker=\"1.\">\n<p data-aid=\"157004959\" id=\"note1_p1\">Véase, por ejemplo, <a class=\"scripture-ref\" href=\"/study/scriptures/ot/isa/49?lang=spa\">Isaías 49<\/a>.<\/p>\n<\/li>\n<li data-marker=\"2.\" id=\"note2\" data-full-marker=\"2.\">\n<p data-aid=\"157004961\" id=\"note2_p1\"><a class=\"scripture-ref\" href=\"/study/scriptures/bofm/2-ne/10.8?lang=spa#p8\">2 Nefi 10:8<\/a>.<\/p>\n<\/li>\n<li data-marker=\"3.\" id=\"note3\" data-full-marker=\"3.\">\n<p data-aid=\"157004963\" id=\"note3_p1\"><a class=\"scripture-ref\" href=\"/study/scriptures/bofm/2-ne/10.7?lang=spa#p7\">2 Nefi 10:7<\/a>.<\/p>\n<\/li>\n<li data-marker=\"4.\" id=\"note4\" data-full-marker=\"4.\">\n<p data-aid=\"157004965\" id=\"note4_p1\">Russell M. Nelson y Wendy W. Nelson, \u201c<a class=\"cross-ref\" href=\"/study/broadcasts/worldwide-devotional-for-young-adults/2018/06/hope-of-israel?lang=spa\">Juventud de Israel<\/a>\u201d, devocional mundial para jóvenes, 3 de junio de 2018, Biblioteca del Evangelio.<\/p>\n<\/li>\n<li data-marker=\"5.\" id=\"note5\" data-full-marker=\"5.\">\n<p data-aid=\"157004967\" id=\"note5_p1\"><a class=\"scripture-ref\" href=\"/study/scriptures/dc-testament/dc/115.6?lang=spa#p6\">Doctrina y Convenios 115:6<\/a>.<\/p>\n<\/li>\n<li data-marker=\"6.\" id=\"note6\" data-full-marker=\"6.\">\n<p data-aid=\"157004969\" id=\"note6_p1\"><a class=\"scripture-ref\" href=\"/study/scriptures/pgp/abr/2.11?lang=spa#p11\">Abraham 2:11<\/a>.<\/p>\n<\/li>\n<li data-marker=\"7.\" id=\"note7\" data-full-marker=\"7.\">\n<p data-aid=\"157004971\" id=\"note7_p1\">Russell M. Nelson, \u201c<a class=\"cross-ref\" href=\"/study/liahona/2022/10/04-the-everlasting-covenant?lang=spa\">El convenio sempiterno<\/a>\u201d, <cite>Liahona<\/cite>, octubre de 2022, pág. 4; véase también Russell M. Nelson, \u201c<a class=\"cross-ref\" href=\"/study/general-conference/1995/04/children-of-the-covenant?lang=spa\">Los hijos del convenio<\/a>\u201d, <cite>Liahona<\/cite>, julio de 1995, pág. 38. \u201cEl \u2018nuevo y sempiterno convenio\u2019 (<a class=\"scripture-ref\" href=\"/study/scriptures/dc-testament/dc/132.6?lang=spa#p6\">Doctrina y Convenios 132:6<\/a>) y el convenio abrahámico son, en esencia, el mismo: son dos maneras de expresar el convenio que Dios hizo con hombres y mujeres mortales en diferentes épocas\u201d (Russel M. Nelson, \u201c<a class=\"cross-ref\" href=\"/study/liahona/2022/10/04-the-everlasting-covenant?lang=spa\">El convenio sempiterno<\/a>\u201d, pág. 4).<\/p>\n<\/li>\n<li data-marker=\"8.\" id=\"note8\" data-full-marker=\"8.\">\n<p data-aid=\"157004973\" id=\"note8_p1\"><a class=\"scripture-ref\" href=\"/study/scriptures/dc-testament/dc/110.11?lang=spa#p11\">Doctrina y Convenios 110:11<\/a>.<\/p>\n<\/li>\n<li data-marker=\"9.\" id=\"note9\" data-full-marker=\"9.\">\n<p data-aid=\"157004975\" id=\"note9_p1\"><a class=\"scripture-ref\" href=\"/study/scriptures/dc-testament/dc/110.12?lang=spa#p12\">Doctrina y Convenios 110:12<\/a>.<\/p>\n<\/li>\n<li data-marker=\"10.\" id=\"note10\" data-full-marker=\"10.\">\n<p data-aid=\"157004977\" id=\"note10_p1\"><a class=\"scripture-ref\" href=\"/study/scriptures/dc-testament/dc/84.34?lang=spa#p34\">Doctrina y Convenios 84:34<\/a>.<\/p>\n<\/li>\n<li data-marker=\"11.\" id=\"note11\" data-full-marker=\"11.\">\n<p data-aid=\"157004979\" id=\"note11_p1\">Véase <a class=\"scripture-ref\" href=\"/study/scriptures/dc-testament/dc/110.13-16?lang=spa#p13\">Doctrina y Convenios 110:13\u201316<\/a>.<\/p>\n<\/li>\n<li data-marker=\"12.\" id=\"note12\" data-full-marker=\"12.\">\n<p data-aid=\"157004982\" id=\"note12_p1\"><a class=\"scripture-ref\" href=\"/study/scriptures/dc-testament/dc/2.1?lang=spa#p1\">Doctrina y Convenios 2:1<\/a>.<\/p>\n<\/li>\n<li data-marker=\"13.\" id=\"note13\" data-full-marker=\"13.\">\n<p data-aid=\"157004984\" id=\"note13_p1\"><cite><a class=\"cross-ref\" href=\"/study/manual/teachings-joseph-smith/chapter-26?lang=spa&amp;para=14#p14\">Enseñanzas de los Presidentes de la Iglesia<\/a><\/cite>: José Smith, 2007, pág. 310.<\/p>\n<\/li>\n<li data-marker=\"14.\" id=\"note14\" data-full-marker=\"14.\">\n<p data-aid=\"157004986\" id=\"note14_p1\">\u201cEl espíritu, poder y llamamiento de Elías el Profeta es el de que ustedes tengan la autoridad de poseer las llaves de la revelación, las ordenanzas, los oráculos, poderes e investiduras de la plenitud del Sacerdocio de Melquisedec y del Reino de Dios en la tierra; y de recibir, obtener y efectuar todas las ordenanzas que pertenecen al Reino de Dios, aun para tornar el corazón de los padres a los hijos, y el corazón de los hijos a los padres, incluso los que estén en los cielos\u201d (<cite><a class=\"cross-ref\" href=\"/study/manual/teachings-joseph-smith/chapter-26?lang=spa&amp;para=19#p19\">Enseñanzas: José Smith<\/a><\/cite>, pág. 329).<\/p>\n<\/li>\n<li data-marker=\"15.\" id=\"note15\" data-full-marker=\"15.\">\n<p data-aid=\"157004989\" id=\"note15_p1\"><a class=\"scripture-ref\" href=\"/study/scriptures/dc-testament/dc/128.9?lang=spa#p9\">Doctrina y Convenios 128:9<\/a>.<\/p>\n<\/li>\n<li data-marker=\"16.\" id=\"note16\" data-full-marker=\"16.\">\n<p data-aid=\"157004992\" id=\"note16_p1\">Véase <a class=\"scripture-ref\" href=\"/study/scriptures/dc-testament/dc/132.7?lang=spa#p7\">Doctrina y Convenios 132:7<\/a>.<\/p>\n<\/li>\n<li data-marker=\"17.\" id=\"note17\" data-full-marker=\"17.\">\n<p data-aid=\"157004994\" id=\"note17_p1\">Joseph Fielding Smith, en Henry B. Eyring, \u201c<a class=\"cross-ref\" href=\"/study/general-conference/2012/04/families-under-covenant?lang=spa\">Familias bajo el convenio<\/a>\u201d, <cite>Liahona<\/cite>, mayo de 2012, pág. 62; véase también la nota 5 en la página 65.<\/p>\n<\/li>\n<li data-marker=\"18.\" id=\"note18\" data-full-marker=\"18.\">\n<p data-aid=\"157004997\" id=\"note18_p1\"><cite><a class=\"cross-ref\" href=\"/study/manual/teachings-joseph-smith/chapter-36?lang=spa&amp;para=15#p15\">Enseñanzas: José Smith<\/a><\/cite>, pág. 443.<\/p>\n<\/li>\n<li data-marker=\"19.\" id=\"note19\" data-full-marker=\"19.\">\n<p data-aid=\"157005000\" id=\"note19_p1\">Sin estos \u201ceslabones conexivos\u201d (véase <a class=\"scripture-ref\" href=\"/study/scriptures/dc-testament/dc/128.18?lang=spa#p18\">Doctrina y Convenios 128:18<\/a>) entre padres e hijos que se crean mediante las ordenanzas del templo, el Señor afirma: \u201cSeréis rechazados [\u2026] junto con vuestros muertos\u201d (<a class=\"scripture-ref\" href=\"/study/scriptures/dc-testament/dc/124.32?lang=spa#p32\">Doctrina y Convenios 124:32<\/a>). No es de extrañar que el Profeta advirtiera: \u201cPermítaseme aseguraros que estos son principios referentes a los muertos y a los vivos que no se pueden desatender, en lo que atañe a nuestra salvación. Porque su salvación es necesaria y esencial para la nuestra, como dice Pablo tocante a los padres: que ellos sin nosotros no pueden ser perfeccionados, ni tampoco podemos nosotros ser perfeccionados sin nuestros muertos\u201d (<a class=\"scripture-ref\" href=\"/study/scriptures/dc-testament/dc/128.15?lang=spa#p15\">Doctrina y Convenios 128:15<\/a>).<\/p>\n<\/li>\n<li data-marker=\"20.\" id=\"note20\" data-full-marker=\"20.\">\n<p data-aid=\"157005003\" id=\"note20_p1\"><cite><a class=\"cross-ref\" href=\"/study/manual/teachings-joseph-smith/chapter-26?lang=spa&amp;para=25#p25\">Enseñanzas: José Smith<\/a><\/cite>, pág. 330.<\/p>\n<\/li>\n<li data-marker=\"21.\" id=\"note21\" data-full-marker=\"21.\">\n<p data-aid=\"157005006\" id=\"note21_p1\">Véase <cite>Teachings of Gordon B. Hinckley<\/cite>, 1997, págs. 475\u2013476.<\/p>\n<\/li>\n<li data-marker=\"22.\" id=\"note22\" data-full-marker=\"22.\">\n<p data-aid=\"157005009\" id=\"note22_p1\">Véase <a class=\"scripture-ref\" href=\"/study/scriptures/dc-testament/dc/132.8-12?lang=spa#p8\">Doctrina y Convenios 132:8\u201312<\/a>.<\/p>\n<\/li>\n<li data-marker=\"23.\" id=\"note23\" data-full-marker=\"23.\">\n<p data-aid=\"157005013\" id=\"note23_p1\">Véanse <a class=\"scripture-ref\" href=\"/study/scriptures/ot/mal/4.6?lang=spa#p6\">Malaquías 4:6<\/a>; <a class=\"scripture-ref\" href=\"/study/scriptures/dc-testament/dc/2.3?lang=spa#p3\">Doctrina y Convenios 2:3<\/a>.<\/p>\n<\/li>\n<li data-marker=\"24.\" id=\"note24\" data-full-marker=\"24.\">\n<p data-aid=\"157005017\" id=\"note24_p1\">\u201c<a class=\"cross-ref\" href=\"/study/scriptures/the-family-a-proclamation-to-the-world/the-family-a-proclamation-to-the-world?lang=spa&amp;verse=title1#title1\">La Familia: Una Proclamación para el Mundo<\/a>\u201d, Biblioteca del Evangelio.<\/p>\n<\/li>\n<li data-marker=\"25.\" id=\"note25\" data-full-marker=\"25.\">\n<p data-aid=\"157005021\" id=\"note25_p1\">M. Russell Ballard, \u201c<a class=\"cross-ref\" href=\"/study/general-conference/2021/04/28ballard?lang=spa\">Esperanza en Cristo<\/a>\u201d, <cite>Liahona<\/cite>, mayo de 2021, pág. 55.<\/p>\n<\/li>\n<li data-marker=\"26.\" id=\"note26\" data-full-marker=\"26.\">\n<p data-aid=\"157005026\" id=\"note26_p1\">Véase David A. Bednar, \u201c<a class=\"cross-ref\" href=\"/study/broadcasts/worldwide-devotional-for-young-adults/2017/09/a-welding-link?lang=spa\">Un eslabón conexivo<\/a>\u201d, devocional mundial para jóvenes adultos, 10 de septiembre de 2017, Biblioteca del Evangelio.<\/p>\n<\/li>\n<\/ol>\n<\/footer>",
    "footnotes": {
      "note4": {
        "marker": "4.",
        "pid": "157004917",
        "id": "note4",
        "text": "<p data-aid=\"157004965\" id=\"note4_p1\">Russell M. Nelson y Wendy W. Nelson, \u201c<a class=\"cross-ref\" href=\"/study/broadcasts/worldwide-devotional-for-young-adults/2018/06/hope-of-israel?lang=spa\">Juventud de Israel<\/a>\u201d, devocional mundial para jóvenes, 3 de junio de 2018, Biblioteca del Evangelio.<\/p>",
        "referenceUris": [{
          "href": "/study/broadcasts/worldwide-devotional-for-young-adults/2018/06/hope-of-israel?lang=spa",
          "text": "Juventud de Israel",
          "type": "cross-ref"
        }]
      },
      "note5": {
        "marker": "5.",
        "pid": "157004921",
        "id": "note5",
        "text": "<p data-aid=\"157004967\" id=\"note5_p1\"><a class=\"scripture-ref\" href=\"/study/scriptures/dc-testament/dc/115.6?lang=spa#p6\">Doctrina y Convenios 115:6<\/a>.<\/p>",
        "referenceUris": [{
          "href": "/study/scriptures/dc-testament/dc/115.6?lang=spa#p6",
          "text": "Doctrina y Convenios 115:6",
          "type": "scripture-ref"
        }]
      },
      "note2": {
        "marker": "2.",
        "pid": "157004917",
        "id": "note2",
        "text": "<p data-aid=\"157004961\" id=\"note2_p1\"><a class=\"scripture-ref\" href=\"/study/scriptures/bofm/2-ne/10.8?lang=spa#p8\">2 Nefi 10:8<\/a>.<\/p>",
        "referenceUris": [{
          "href": "/study/scriptures/bofm/2-ne/10.8?lang=spa#p8",
          "text": "2 Nefi 10:8",
          "type": "scripture-ref"
        }]
      },
      "note3": {
        "marker": "3.",
        "pid": "157004917",
        "id": "note3",
        "text": "<p data-aid=\"157004963\" id=\"note3_p1\"><a class=\"scripture-ref\" href=\"/study/scriptures/bofm/2-ne/10.7?lang=spa#p7\">2 Nefi 10:7<\/a>.<\/p>",
        "referenceUris": [{
          "href": "/study/scriptures/bofm/2-ne/10.7?lang=spa#p7",
          "text": "2 Nefi 10:7",
          "type": "scripture-ref"
        }]
      },
      "note8": {
        "marker": "8.",
        "pid": "157004925",
        "id": "note8",
        "text": "<p data-aid=\"157004973\" id=\"note8_p1\"><a class=\"scripture-ref\" href=\"/study/scriptures/dc-testament/dc/110.11?lang=spa#p11\">Doctrina y Convenios 110:11<\/a>.<\/p>",
        "referenceUris": [{
          "href": "/study/scriptures/dc-testament/dc/110.11?lang=spa#p11",
          "text": "Doctrina y Convenios 110:11",
          "type": "scripture-ref"
        }]
      },
      "note9": {
        "marker": "9.",
        "pid": "157004925",
        "id": "note9",
        "text": "<p data-aid=\"157004975\" id=\"note9_p1\"><a class=\"scripture-ref\" href=\"/study/scriptures/dc-testament/dc/110.12?lang=spa#p12\">Doctrina y Convenios 110:12<\/a>.<\/p>",
        "referenceUris": [{
          "href": "/study/scriptures/dc-testament/dc/110.12?lang=spa#p12",
          "text": "Doctrina y Convenios 110:12",
          "type": "scripture-ref"
        }]
      },
      "note6": {
        "marker": "6.",
        "pid": "157004923",
        "id": "note6",
        "text": "<p data-aid=\"157004969\" id=\"note6_p1\"><a class=\"scripture-ref\" href=\"/study/scriptures/pgp/abr/2.11?lang=spa#p11\">Abraham 2:11<\/a>.<\/p>",
        "referenceUris": [{
          "href": "/study/scriptures/pgp/abr/2.11?lang=spa#p11",
          "text": "Abraham 2:11",
          "type": "scripture-ref"
        }]
      },
      "note7": {
        "marker": "7.",
        "pid": "157004923",
        "id": "note7",
        "text": "<p data-aid=\"157004971\" id=\"note7_p1\">Russell M. Nelson, \u201c<a class=\"cross-ref\" href=\"/study/liahona/2022/10/04-the-everlasting-covenant?lang=spa\">El convenio sempiterno<\/a>\u201d, <cite>Liahona<\/cite>, octubre de 2022, pág. 4; véase también Russell M. Nelson, \u201c<a class=\"cross-ref\" href=\"/study/general-conference/1995/04/children-of-the-covenant?lang=spa\">Los hijos del convenio<\/a>\u201d, <cite>Liahona<\/cite>, julio de 1995, pág. 38. \u201cEl \u2018nuevo y sempiterno convenio\u2019 (<a class=\"scripture-ref\" href=\"/study/scriptures/dc-testament/dc/132.6?lang=spa#p6\">Doctrina y Convenios 132:6<\/a>) y el convenio abrahámico son, en esencia, el mismo: son dos maneras de expresar el convenio que Dios hizo con hombres y mujeres mortales en diferentes épocas\u201d (Russel M. Nelson, \u201c<a class=\"cross-ref\" href=\"/study/liahona/2022/10/04-the-everlasting-covenant?lang=spa\">El convenio sempiterno<\/a>\u201d, pág. 4).<\/p>",
        "referenceUris": [
          {
            "href": "/study/liahona/2022/10/04-the-everlasting-covenant?lang=spa",
            "text": "El convenio sempiterno",
            "type": "cross-ref"
          },
          {
            "href": "/study/general-conference/1995/04/children-of-the-covenant?lang=spa",
            "text": "Los hijos del convenio",
            "type": "cross-ref"
          },
          {
            "href": "/study/scriptures/dc-testament/dc/132.6?lang=spa#p6",
            "text": "Doctrina y Convenios 132:6",
            "type": "scripture-ref"
          },
          {
            "href": "/study/liahona/2022/10/04-the-everlasting-covenant?lang=spa",
            "text": "El convenio sempiterno",
            "type": "cross-ref"
          }
        ]
      },
      "note16": {
        "marker": "16.",
        "pid": "157004933",
        "id": "note16",
        "text": "<p data-aid=\"157004992\" id=\"note16_p1\">Véase <a class=\"scripture-ref\" href=\"/study/scriptures/dc-testament/dc/132.7?lang=spa#p7\">Doctrina y Convenios 132:7<\/a>.<\/p>",
        "referenceUris": [{
          "href": "/study/scriptures/dc-testament/dc/132.7?lang=spa#p7",
          "text": "Doctrina y Convenios 132:7",
          "type": "scripture-ref"
        }]
      },
      "note15": {
        "marker": "15.",
        "pid": "157004931",
        "id": "note15",
        "text": "<p data-aid=\"157004989\" id=\"note15_p1\"><a class=\"scripture-ref\" href=\"/study/scriptures/dc-testament/dc/128.9?lang=spa#p9\">Doctrina y Convenios 128:9<\/a>.<\/p>",
        "referenceUris": [{
          "href": "/study/scriptures/dc-testament/dc/128.9?lang=spa#p9",
          "text": "Doctrina y Convenios 128:9",
          "type": "scripture-ref"
        }]
      },
      "note14": {
        "marker": "14.",
        "pid": "157004929",
        "id": "note14",
        "text": "<p data-aid=\"157004986\" id=\"note14_p1\">\u201cEl espíritu, poder y llamamiento de Elías el Profeta es el de que ustedes tengan la autoridad de poseer las llaves de la revelación, las ordenanzas, los oráculos, poderes e investiduras de la plenitud del Sacerdocio de Melquisedec y del Reino de Dios en la tierra; y de recibir, obtener y efectuar todas las ordenanzas que pertenecen al Reino de Dios, aun para tornar el corazón de los padres a los hijos, y el corazón de los hijos a los padres, incluso los que estén en los cielos\u201d (<cite><a class=\"cross-ref\" href=\"/study/manual/teachings-joseph-smith/chapter-26?lang=spa&amp;para=19#p19\">Enseñanzas: José Smith<\/a><\/cite>, pág. 329).<\/p>",
        "referenceUris": [{
          "href": "/study/manual/teachings-joseph-smith/chapter-26?lang=spa&amp;para=19#p19",
          "text": "Enseñanzas: José Smith",
          "type": "cross-ref"
        }]
      },
      "note13": {
        "marker": "13.",
        "pid": "157004929",
        "id": "note13",
        "text": "<p data-aid=\"157004984\" id=\"note13_p1\"><cite><a class=\"cross-ref\" href=\"/study/manual/teachings-joseph-smith/chapter-26?lang=spa&amp;para=14#p14\">Enseñanzas de los Presidentes de la Iglesia<\/a><\/cite>: José Smith, 2007, pág. 310.<\/p>",
        "referenceUris": [{
          "href": "/study/manual/teachings-joseph-smith/chapter-26?lang=spa&amp;para=14#p14",
          "text": "Enseñanzas de los Presidentes de la Iglesia",
          "type": "cross-ref"
        }]
      },
      "note12": {
        "marker": "12.",
        "pid": "157004929",
        "id": "note12",
        "text": "<p data-aid=\"157004982\" id=\"note12_p1\"><a class=\"scripture-ref\" href=\"/study/scriptures/dc-testament/dc/2.1?lang=spa#p1\">Doctrina y Convenios 2:1<\/a>.<\/p>",
        "referenceUris": [{
          "href": "/study/scriptures/dc-testament/dc/2.1?lang=spa#p1",
          "text": "Doctrina y Convenios 2:1",
          "type": "scripture-ref"
        }]
      },
      "note11": {
        "marker": "11.",
        "pid": "157004927",
        "id": "note11",
        "text": "<p data-aid=\"157004979\" id=\"note11_p1\">Véase <a class=\"scripture-ref\" href=\"/study/scriptures/dc-testament/dc/110.13-16?lang=spa#p13\">Doctrina y Convenios 110:13\u201316<\/a>.<\/p>",
        "referenceUris": [{
          "href": "/study/scriptures/dc-testament/dc/110.13-16?lang=spa#p13",
          "text": "Doctrina y Convenios 110:13\u201316",
          "type": "scripture-ref"
        }]
      },
      "note10": {
        "marker": "10.",
        "pid": "157004925",
        "id": "note10",
        "text": "<p data-aid=\"157004977\" id=\"note10_p1\"><a class=\"scripture-ref\" href=\"/study/scriptures/dc-testament/dc/84.34?lang=spa#p34\">Doctrina y Convenios 84:34<\/a>.<\/p>",
        "referenceUris": [{
          "href": "/study/scriptures/dc-testament/dc/84.34?lang=spa#p34",
          "text": "Doctrina y Convenios 84:34",
          "type": "scripture-ref"
        }]
      },
      "note19": {
        "marker": "19.",
        "pid": "157004939",
        "id": "note19",
        "text": "<p data-aid=\"157005000\" id=\"note19_p1\">Sin estos \u201ceslabones conexivos\u201d (véase <a class=\"scripture-ref\" href=\"/study/scriptures/dc-testament/dc/128.18?lang=spa#p18\">Doctrina y Convenios 128:18<\/a>) entre padres e hijos que se crean mediante las ordenanzas del templo, el Señor afirma: \u201cSeréis rechazados [\u2026] junto con vuestros muertos\u201d (<a class=\"scripture-ref\" href=\"/study/scriptures/dc-testament/dc/124.32?lang=spa#p32\">Doctrina y Convenios 124:32<\/a>). No es de extrañar que el Profeta advirtiera: \u201cPermítaseme aseguraros que estos son principios referentes a los muertos y a los vivos que no se pueden desatender, en lo que atañe a nuestra salvación. Porque su salvación es necesaria y esencial para la nuestra, como dice Pablo tocante a los padres: que ellos sin nosotros no pueden ser perfeccionados, ni tampoco podemos nosotros ser perfeccionados sin nuestros muertos\u201d (<a class=\"scripture-ref\" href=\"/study/scriptures/dc-testament/dc/128.15?lang=spa#p15\">Doctrina y Convenios 128:15<\/a>).<\/p>",
        "referenceUris": [
          {
            "href": "/study/scriptures/dc-testament/dc/128.18?lang=spa#p18",
            "text": "Doctrina y Convenios 128:18",
            "type": "scripture-ref"
          },
          {
            "href": "/study/scriptures/dc-testament/dc/124.32?lang=spa#p32",
            "text": "Doctrina y Convenios 124:32",
            "type": "scripture-ref"
          },
          {
            "href": "/study/scriptures/dc-testament/dc/128.15?lang=spa#p15",
            "text": "Doctrina y Convenios 128:15",
            "type": "scripture-ref"
          }
        ]
      },
      "note18": {
        "marker": "18.",
        "pid": "157004935",
        "id": "note18",
        "text": "<p data-aid=\"157004997\" id=\"note18_p1\"><cite><a class=\"cross-ref\" href=\"/study/manual/teachings-joseph-smith/chapter-36?lang=spa&amp;para=15#p15\">Enseñanzas: José Smith<\/a><\/cite>, pág. 443.<\/p>",
        "referenceUris": [{
          "href": "/study/manual/teachings-joseph-smith/chapter-36?lang=spa&amp;para=15#p15",
          "text": "Enseñanzas: José Smith",
          "type": "cross-ref"
        }]
      },
      "note17": {
        "marker": "17.",
        "pid": "157004933",
        "id": "note17",
        "text": "<p data-aid=\"157004994\" id=\"note17_p1\">Joseph Fielding Smith, en Henry B. Eyring, \u201c<a class=\"cross-ref\" href=\"/study/general-conference/2012/04/families-under-covenant?lang=spa\">Familias bajo el convenio<\/a>\u201d, <cite>Liahona<\/cite>, mayo de 2012, pág. 62; véase también la nota 5 en la página 65.<\/p>",
        "referenceUris": [{
          "href": "/study/general-conference/2012/04/families-under-covenant?lang=spa",
          "text": "Familias bajo el convenio",
          "type": "cross-ref"
        }]
      },
      "note26": {
        "marker": "26.",
        "pid": "157004946",
        "id": "note26",
        "text": "<p data-aid=\"157005026\" id=\"note26_p1\">Véase David A. Bednar, \u201c<a class=\"cross-ref\" href=\"/study/broadcasts/worldwide-devotional-for-young-adults/2017/09/a-welding-link?lang=spa\">Un eslabón conexivo<\/a>\u201d, devocional mundial para jóvenes adultos, 10 de septiembre de 2017, Biblioteca del Evangelio.<\/p>",
        "referenceUris": [{
          "href": "/study/broadcasts/worldwide-devotional-for-young-adults/2017/09/a-welding-link?lang=spa",
          "text": "Un eslabón conexivo",
          "type": "cross-ref"
        }]
      },
      "note25": {
        "marker": "25.",
        "pid": "157004944",
        "id": "note25",
        "text": "<p data-aid=\"157005021\" id=\"note25_p1\">M. Russell Ballard, \u201c<a class=\"cross-ref\" href=\"/study/general-conference/2021/04/28ballard?lang=spa\">Esperanza en Cristo<\/a>\u201d, <cite>Liahona<\/cite>, mayo de 2021, pág. 55.<\/p>",
        "referenceUris": [{
          "href": "/study/general-conference/2021/04/28ballard?lang=spa",
          "text": "Esperanza en Cristo",
          "type": "cross-ref"
        }]
      },
      "note24": {
        "marker": "24.",
        "pid": "157004944",
        "id": "note24",
        "text": "<p data-aid=\"157005017\" id=\"note24_p1\">\u201c<a class=\"cross-ref\" href=\"/study/scriptures/the-family-a-proclamation-to-the-world/the-family-a-proclamation-to-the-world?lang=spa&amp;verse=title1#title1\">La Familia: Una Proclamación para el Mundo<\/a>\u201d, Biblioteca del Evangelio.<\/p>",
        "referenceUris": [{
          "href": "/study/scriptures/the-family-a-proclamation-to-the-world/the-family-a-proclamation-to-the-world?lang=spa&amp;verse=title1#title1",
          "text": "La Familia: Una Proclamación para el Mundo",
          "type": "cross-ref"
        }]
      },
      "note23": {
        "marker": "23.",
        "pid": "157004943",
        "id": "note23",
        "text": "<p data-aid=\"157005013\" id=\"note23_p1\">Véanse <a class=\"scripture-ref\" href=\"/study/scriptures/ot/mal/4.6?lang=spa#p6\">Malaquías 4:6<\/a>; <a class=\"scripture-ref\" href=\"/study/scriptures/dc-testament/dc/2.3?lang=spa#p3\">Doctrina y Convenios 2:3<\/a>.<\/p>",
        "referenceUris": [
          {
            "href": "/study/scriptures/ot/mal/4.6?lang=spa#p6",
            "text": "Malaquías 4:6",
            "type": "scripture-ref"
          },
          {
            "href": "/study/scriptures/dc-testament/dc/2.3?lang=spa#p3",
            "text": "Doctrina y Convenios 2:3",
            "type": "scripture-ref"
          }
        ]
      },
      "note22": {
        "marker": "22.",
        "pid": "157004943",
        "id": "note22",
        "text": "<p data-aid=\"157005009\" id=\"note22_p1\">Véase <a class=\"scripture-ref\" href=\"/study/scriptures/dc-testament/dc/132.8-12?lang=spa#p8\">Doctrina y Convenios 132:8\u201312<\/a>.<\/p>",
        "referenceUris": [{
          "href": "/study/scriptures/dc-testament/dc/132.8-12?lang=spa#p8",
          "text": "Doctrina y Convenios 132:8\u201312",
          "type": "scripture-ref"
        }]
      },
      "note21": {
        "marker": "21.",
        "pid": "157004941",
        "id": "note21",
        "text": "<p data-aid=\"157005006\" id=\"note21_p1\">Véase <cite>Teachings of Gordon B. Hinckley<\/cite>, 1997, págs. 475\u2013476.<\/p>"
      },
      "note20": {
        "marker": "20.",
        "pid": "157004939",
        "id": "note20",
        "text": "<p data-aid=\"157005003\" id=\"note20_p1\"><cite><a class=\"cross-ref\" href=\"/study/manual/teachings-joseph-smith/chapter-26?lang=spa&amp;para=25#p25\">Enseñanzas: José Smith<\/a><\/cite>, pág. 330.<\/p>",
        "referenceUris": [{
          "href": "/study/manual/teachings-joseph-smith/chapter-26?lang=spa&amp;para=25#p25",
          "text": "Enseñanzas: José Smith",
          "type": "cross-ref"
        }]
      },
      "note1": {
        "marker": "1.",
        "pid": "157004917",
        "id": "note1",
        "text": "<p data-aid=\"157004959\" id=\"note1_p1\">Véase, por ejemplo, <a class=\"scripture-ref\" href=\"/study/scriptures/ot/isa/49?lang=spa\">Isaías 49<\/a>.<\/p>",
        "referenceUris": [{
          "href": "/study/scriptures/ot/isa/49?lang=spa",
          "text": "Isaías 49",
          "type": "scripture-ref"
        }]
      }
    }
  }
}